lofty.py
bsit_lofty-0.1.1.dist-info/licenses/LICENSE
bsit_lofty-0.1.1.dist-info/METADATA
bsit_lofty-0.1.1.dist-info/WHEEL
bsit_lofty-0.1.1.dist-info/top_level.txt
bsit_lofty-0.1.1.dist-info/RECORD
