Metadata-Version: 2.4
Name: bsit-lofty
Version: 0.1.1
Summary: BACnet Semantic Interoperability Toolkit - Lofty - Real Estate Core
Requires-Python: >=3.13
License-File: LICENSE
Requires-Dist: bsit-bob>=0.1.0
Requires-Dist: rdflib>=7.1.4
Dynamic: license-file
